{
    "php-82": {
        "ca-central-1": "22",
        "eu-central-1": "22",
        "eu-north-1": "22",
        "eu-west-1": "22",
        "eu-west-2": "22",
        "eu-west-3": "22",
        "sa-east-1": "22",
        "us-east-1": "22",
        "us-east-2": "22",
        "us-west-1": "22",
        "us-west-2": "22",
        "ap-east-1": "22",
        "ap-south-1": "22",
        "ap-northeast-1": "22",
        "ap-northeast-2": "22",
        "ap-northeast-3": "22",
        "ap-southeast-1": "22",
        "ap-southeast-2": "22",
        "eu-south-1": "22",
        "eu-south-2": "21",
        "af-south-1": "22",
        "me-south-1": "22"
    },
    "php-82-fpm": {
        "ca-central-1": "22",
        "eu-central-1": "22",
        "eu-north-1": "22",
        "eu-west-1": "22",
        "eu-west-2": "22",
        "eu-west-3": "22",
        "sa-east-1": "22",
        "us-east-1": "22",
        "us-east-2": "22",
        "us-west-1": "22",
        "us-west-2": "22",
        "ap-east-1": "22",
        "ap-south-1": "22",
        "ap-northeast-1": "22",
        "ap-northeast-2": "22",
        "ap-northeast-3": "22",
        "ap-southeast-1": "22",
        "ap-southeast-2": "22",
        "eu-south-1": "22",
        "eu-south-2": "21",
        "af-south-1": "22",
        "me-south-1": "22"
    },
    "php-81": {
        "ca-central-1": "32",
        "eu-central-1": "32",
        "eu-north-1": "32",
        "eu-west-1": "32",
        "eu-west-2": "32",
        "eu-west-3": "32",
        "sa-east-1": "32",
        "us-east-1": "32",
        "us-east-2": "32",
        "us-west-1": "32",
        "us-west-2": "32",
        "ap-east-1": "24",
        "ap-south-1": "31",
        "ap-northeast-1": "31",
        "ap-northeast-2": "31",
        "ap-northeast-3": "31",
        "ap-southeast-1": "31",
        "ap-southeast-2": "31",
        "eu-south-1": "24",
        "eu-south-2": "21",
        "af-south-1": "24",
        "me-south-1": "24"
    },
    "php-81-fpm": {
        "ca-central-1": "32",
        "eu-central-1": "32",
        "eu-north-1": "32",
        "eu-west-1": "32",
        "eu-west-2": "32",
        "eu-west-3": "32",
        "sa-east-1": "32",
        "us-east-1": "32",
        "us-east-2": "32",
        "us-west-1": "32",
        "us-west-2": "32",
        "ap-east-1": "24",
        "ap-south-1": "31",
        "ap-northeast-1": "31",
        "ap-northeast-2": "31",
        "ap-northeast-3": "31",
        "ap-southeast-1": "31",
        "ap-southeast-2": "31",
        "eu-south-1": "24",
        "eu-south-2": "21",
        "af-south-1": "24",
        "me-south-1": "24"
    },
    "php-80": {
        "ca-central-1": "34",
        "eu-central-1": "34",
        "eu-north-1": "34",
        "eu-west-1": "34",
        "eu-west-2": "34",
        "eu-west-3": "34",
        "sa-east-1": "34",
        "us-east-1": "34",
        "us-east-2": "34",
        "us-west-1": "34",
        "us-west-2": "34",
        "ap-east-1": "24",
        "ap-south-1": "33",
        "ap-northeast-1": "31",
        "ap-northeast-2": "31",
        "ap-northeast-3": "31",
        "ap-southeast-1": "31",
        "ap-southeast-2": "33",
        "eu-south-1": "24",
        "eu-south-2": "21",
        "af-south-1": "24",
        "me-south-1": "24"
    },
    "php-80-fpm": {
        "ca-central-1": "32",
        "eu-central-1": "32",
        "eu-north-1": "32",
        "eu-west-1": "32",
        "eu-west-2": "32",
        "eu-west-3": "32",
        "sa-east-1": "32",
        "us-east-1": "32",
        "us-east-2": "32",
        "us-west-1": "32",
        "us-west-2": "32",
        "ap-east-1": "24",
        "ap-south-1": "31",
        "ap-northeast-1": "31",
        "ap-northeast-2": "31",
        "ap-northeast-3": "31",
        "ap-southeast-1": "31",
        "ap-southeast-2": "31",
        "eu-south-1": "24",
        "eu-south-2": "21",
        "af-south-1": "24",
        "me-south-1": "24"
    },
    "arm-php-82": {
        "ca-central-1": "9",
        "eu-central-1": "9",
        "eu-north-1": "9",
        "eu-west-1": "9",
        "eu-west-2": "9",
        "eu-west-3": "9",
        "sa-east-1": "9",
        "us-east-1": "9",
        "us-east-2": "9",
        "us-west-1": "9",
        "us-west-2": "9",
        "ap-east-1": "9",
        "ap-south-1": "9",
        "ap-northeast-1": "9",
        "ap-northeast-2": "9",
        "ap-northeast-3": "9",
        "ap-southeast-1": "9",
        "ap-southeast-2": "9",
        "eu-south-1": "9",
        "eu-south-2": "9",
        "af-south-1": "9",
        "me-south-1": "9"
    },
    "arm-php-82-fpm": {
        "ca-central-1": "9",
        "eu-central-1": "9",
        "eu-north-1": "9",
        "eu-west-1": "9",
        "eu-west-2": "9",
        "eu-west-3": "9",
        "sa-east-1": "9",
        "us-east-1": "9",
        "us-east-2": "9",
        "us-west-1": "9",
        "us-west-2": "9",
        "ap-east-1": "9",
        "ap-south-1": "9",
        "ap-northeast-1": "9",
        "ap-northeast-2": "9",
        "ap-northeast-3": "9",
        "ap-southeast-1": "9",
        "ap-southeast-2": "9",
        "eu-south-1": "9",
        "eu-south-2": "9",
        "af-south-1": "9",
        "me-south-1": "9"
    },
    "arm-php-81": {
        "ca-central-1": "12",
        "eu-central-1": "12",
        "eu-north-1": "12",
        "eu-west-1": "12",
        "eu-west-2": "12",
        "eu-west-3": "12",
        "sa-east-1": "12",
        "us-east-1": "12",
        "us-east-2": "12",
        "us-west-1": "12",
        "us-west-2": "12",
        "ap-east-1": "12",
        "ap-south-1": "12",
        "ap-northeast-1": "12",
        "ap-northeast-2": "12",
        "ap-northeast-3": "12",
        "ap-southeast-1": "12",
        "ap-southeast-2": "12",
        "eu-south-1": "12",
        "eu-south-2": "12",
        "af-south-1": "12",
        "me-south-1": "12"
    },
    "arm-php-81-fpm": {
        "ca-central-1": "12",
        "eu-central-1": "12",
        "eu-north-1": "12",
        "eu-west-1": "12",
        "eu-west-2": "12",
        "eu-west-3": "12",
        "sa-east-1": "12",
        "us-east-1": "12",
        "us-east-2": "12",
        "us-west-1": "12",
        "us-west-2": "12",
        "ap-east-1": "12",
        "ap-south-1": "12",
        "ap-northeast-1": "12",
        "ap-northeast-2": "12",
        "ap-northeast-3": "12",
        "ap-southeast-1": "12",
        "ap-southeast-2": "12",
        "eu-south-1": "12",
        "eu-south-2": "12",
        "af-south-1": "12",
        "me-south-1": "12"
    },
    "arm-php-80": {
        "ca-central-1": "33",
        "eu-central-1": "32",
        "eu-north-1": "33",
        "eu-west-1": "33",
        "eu-west-2": "33",
        "eu-west-3": "33",
        "sa-east-1": "33",
        "us-east-1": "33",
        "us-east-2": "33",
        "us-west-1": "33",
        "us-west-2": "33",
        "ap-east-1": "25",
        "ap-south-1": "32",
        "ap-northeast-1": "32",
        "ap-northeast-2": "32",
        "ap-northeast-3": "32",
        "ap-southeast-1": "32",
        "ap-southeast-2": "32",
        "eu-south-1": "25",
        "eu-south-2": "21",
        "af-south-1": "25",
        "me-south-1": "25"
    },
    "arm-php-80-fpm": {
        "ca-central-1": "32",
        "eu-central-1": "32",
        "eu-north-1": "32",
        "eu-west-1": "32",
        "eu-west-2": "32",
        "eu-west-3": "32",
        "sa-east-1": "32",
        "us-east-1": "32",
        "us-east-2": "32",
        "us-west-1": "32",
        "us-west-2": "32",
        "ap-east-1": "24",
        "ap-south-1": "31",
        "ap-northeast-1": "31",
        "ap-northeast-2": "31",
        "ap-northeast-3": "31",
        "ap-southeast-1": "31",
        "ap-southeast-2": "31",
        "eu-south-1": "24",
        "eu-south-2": "21",
        "af-south-1": "24",
        "me-south-1": "24"
    },
    "console": {
        "ca-central-1": "32",
        "eu-central-1": "32",
        "eu-north-1": "32",
        "eu-west-1": "32",
        "eu-west-2": "32",
        "eu-west-3": "32",
        "sa-east-1": "32",
        "us-east-1": "32",
        "us-east-2": "32",
        "us-west-1": "32",
        "us-west-2": "32",
        "ap-east-1": "24",
        "ap-south-1": "31",
        "ap-northeast-1": "31",
        "ap-northeast-2": "31",
        "ap-northeast-3": "31",
        "ap-southeast-1": "31",
        "ap-southeast-2": "31",
        "eu-south-1": "24",
        "eu-south-2": "21",
        "af-south-1": "24",
        "me-south-1": "24"
    }
}