{
    "php-83": {
        "ca-central-1": "8",
        "eu-central-1": "8",
        "eu-north-1": "8",
        "eu-west-1": "8",
        "eu-west-2": "8",
        "eu-west-3": "8",
        "sa-east-1": "8",
        "us-east-1": "8",
        "us-east-2": "8",
        "us-west-1": "8",
        "us-west-2": "8",
        "ap-east-1": "8",
        "ap-south-1": "8",
        "ap-northeast-1": "8",
        "ap-northeast-2": "8",
        "ap-northeast-3": "8",
        "ap-southeast-1": "8",
        "ap-southeast-2": "8",
        "eu-south-1": "8",
        "eu-south-2": "8",
        "af-south-1": "8",
        "me-south-1": "8"
    },
    "php-83-fpm": {
        "ca-central-1": "8",
        "eu-central-1": "8",
        "eu-north-1": "8",
        "eu-west-1": "8",
        "eu-west-2": "8",
        "eu-west-3": "8",
        "sa-east-1": "8",
        "us-east-1": "8",
        "us-east-2": "8",
        "us-west-1": "8",
        "us-west-2": "8",
        "ap-east-1": "8",
        "ap-south-1": "8",
        "ap-northeast-1": "8",
        "ap-northeast-2": "8",
        "ap-northeast-3": "8",
        "ap-southeast-1": "8",
        "ap-southeast-2": "8",
        "eu-south-1": "8",
        "eu-south-2": "8",
        "af-south-1": "8",
        "me-south-1": "8"
    },
    "php-82": {
        "ca-central-1": "52",
        "eu-central-1": "52",
        "eu-north-1": "52",
        "eu-west-1": "52",
        "eu-west-2": "52",
        "eu-west-3": "52",
        "sa-east-1": "52",
        "us-east-1": "52",
        "us-east-2": "52",
        "us-west-1": "52",
        "us-west-2": "52",
        "ap-east-1": "52",
        "ap-south-1": "52",
        "ap-northeast-1": "52",
        "ap-northeast-2": "52",
        "ap-northeast-3": "52",
        "ap-southeast-1": "52",
        "ap-southeast-2": "52",
        "eu-south-1": "52",
        "eu-south-2": "51",
        "af-south-1": "52",
        "me-south-1": "52"
    },
    "php-82-fpm": {
        "ca-central-1": "52",
        "eu-central-1": "52",
        "eu-north-1": "52",
        "eu-west-1": "52",
        "eu-west-2": "52",
        "eu-west-3": "52",
        "sa-east-1": "52",
        "us-east-1": "52",
        "us-east-2": "52",
        "us-west-1": "52",
        "us-west-2": "52",
        "ap-east-1": "52",
        "ap-south-1": "52",
        "ap-northeast-1": "52",
        "ap-northeast-2": "52",
        "ap-northeast-3": "52",
        "ap-southeast-1": "52",
        "ap-southeast-2": "52",
        "eu-south-1": "52",
        "eu-south-2": "51",
        "af-south-1": "52",
        "me-south-1": "52"
    },
    "php-81": {
        "ca-central-1": "63",
        "eu-central-1": "63",
        "eu-north-1": "63",
        "eu-west-1": "63",
        "eu-west-2": "63",
        "eu-west-3": "63",
        "sa-east-1": "63",
        "us-east-1": "63",
        "us-east-2": "63",
        "us-west-1": "63",
        "us-west-2": "63",
        "ap-east-1": "55",
        "ap-south-1": "62",
        "ap-northeast-1": "62",
        "ap-northeast-2": "62",
        "ap-northeast-3": "62",
        "ap-southeast-1": "62",
        "ap-southeast-2": "62",
        "eu-south-1": "55",
        "eu-south-2": "52",
        "af-south-1": "55",
        "me-south-1": "55"
    },
    "php-81-fpm": {
        "ca-central-1": "62",
        "eu-central-1": "62",
        "eu-north-1": "63",
        "eu-west-1": "63",
        "eu-west-2": "62",
        "eu-west-3": "62",
        "sa-east-1": "62",
        "us-east-1": "63",
        "us-east-2": "62",
        "us-west-1": "62",
        "us-west-2": "63",
        "ap-east-1": "55",
        "ap-south-1": "61",
        "ap-northeast-1": "62",
        "ap-northeast-2": "61",
        "ap-northeast-3": "61",
        "ap-southeast-1": "61",
        "ap-southeast-2": "61",
        "eu-south-1": "54",
        "eu-south-2": "51",
        "af-south-1": "54",
        "me-south-1": "54"
    },
    "php-80": {
        "ca-central-1": "66",
        "eu-central-1": "65",
        "eu-north-1": "66",
        "eu-west-1": "66",
        "eu-west-2": "66",
        "eu-west-3": "66",
        "sa-east-1": "66",
        "us-east-1": "66",
        "us-east-2": "66",
        "us-west-1": "66",
        "us-west-2": "66",
        "ap-east-1": "56",
        "ap-south-1": "65",
        "ap-northeast-1": "63",
        "ap-northeast-2": "62",
        "ap-northeast-3": "63",
        "ap-southeast-1": "62",
        "ap-southeast-2": "64",
        "eu-south-1": "56",
        "eu-south-2": "52",
        "af-south-1": "56",
        "me-south-1": "56"
    },
    "php-80-fpm": {
        "ca-central-1": "63",
        "eu-central-1": "63",
        "eu-north-1": "63",
        "eu-west-1": "63",
        "eu-west-2": "63",
        "eu-west-3": "63",
        "sa-east-1": "63",
        "us-east-1": "63",
        "us-east-2": "63",
        "us-west-1": "63",
        "us-west-2": "63",
        "ap-east-1": "55",
        "ap-south-1": "62",
        "ap-northeast-1": "62",
        "ap-northeast-2": "62",
        "ap-northeast-3": "62",
        "ap-southeast-1": "62",
        "ap-southeast-2": "62",
        "eu-south-1": "55",
        "eu-south-2": "52",
        "af-south-1": "55",
        "me-south-1": "55"
    },
    "arm-php-83": {
        "ca-central-1": "8",
        "eu-central-1": "8",
        "eu-north-1": "8",
        "eu-west-1": "8",
        "eu-west-2": "8",
        "eu-west-3": "8",
        "sa-east-1": "8",
        "us-east-1": "8",
        "us-east-2": "8",
        "us-west-1": "8",
        "us-west-2": "8",
        "ap-east-1": "8",
        "ap-south-1": "8",
        "ap-northeast-1": "8",
        "ap-northeast-2": "8",
        "ap-northeast-3": "8",
        "ap-southeast-1": "8",
        "ap-southeast-2": "8",
        "eu-south-1": "8",
        "eu-south-2": "8",
        "af-south-1": "8",
        "me-south-1": "8"
    },
    "arm-php-83-fpm": {
        "ca-central-1": "8",
        "eu-central-1": "8",
        "eu-north-1": "8",
        "eu-west-1": "8",
        "eu-west-2": "8",
        "eu-west-3": "8",
        "sa-east-1": "8",
        "us-east-1": "8",
        "us-east-2": "8",
        "us-west-1": "8",
        "us-west-2": "8",
        "ap-east-1": "8",
        "ap-south-1": "8",
        "ap-northeast-1": "8",
        "ap-northeast-2": "8",
        "ap-northeast-3": "8",
        "ap-southeast-1": "8",
        "ap-southeast-2": "8",
        "eu-south-1": "8",
        "eu-south-2": "8",
        "af-south-1": "8",
        "me-south-1": "8"
    },
    "arm-php-82": {
        "ca-central-1": "40",
        "eu-central-1": "40",
        "eu-north-1": "40",
        "eu-west-1": "40",
        "eu-west-2": "40",
        "eu-west-3": "40",
        "sa-east-1": "40",
        "us-east-1": "40",
        "us-east-2": "40",
        "us-west-1": "40",
        "us-west-2": "40",
        "ap-east-1": "40",
        "ap-south-1": "40",
        "ap-northeast-1": "40",
        "ap-northeast-2": "40",
        "ap-northeast-3": "40",
        "ap-southeast-1": "40",
        "ap-southeast-2": "40",
        "eu-south-1": "40",
        "eu-south-2": "40",
        "af-south-1": "40",
        "me-south-1": "40"
    },
    "arm-php-82-fpm": {
        "ca-central-1": "40",
        "eu-central-1": "40",
        "eu-north-1": "40",
        "eu-west-1": "40",
        "eu-west-2": "40",
        "eu-west-3": "40",
        "sa-east-1": "40",
        "us-east-1": "40",
        "us-east-2": "40",
        "us-west-1": "40",
        "us-west-2": "40",
        "ap-east-1": "40",
        "ap-south-1": "40",
        "ap-northeast-1": "40",
        "ap-northeast-2": "40",
        "ap-northeast-3": "40",
        "ap-southeast-1": "40",
        "ap-southeast-2": "40",
        "eu-south-1": "40",
        "eu-south-2": "40",
        "af-south-1": "40",
        "me-south-1": "40"
    },
    "arm-php-81": {
        "ca-central-1": "43",
        "eu-central-1": "43",
        "eu-north-1": "43",
        "eu-west-1": "43",
        "eu-west-2": "43",
        "eu-west-3": "43",
        "sa-east-1": "43",
        "us-east-1": "43",
        "us-east-2": "43",
        "us-west-1": "43",
        "us-west-2": "43",
        "ap-east-1": "43",
        "ap-south-1": "43",
        "ap-northeast-1": "43",
        "ap-northeast-2": "43",
        "ap-northeast-3": "43",
        "ap-southeast-1": "43",
        "ap-southeast-2": "43",
        "eu-south-1": "43",
        "eu-south-2": "43",
        "af-south-1": "43",
        "me-south-1": "43"
    },
    "arm-php-81-fpm": {
        "ca-central-1": "43",
        "eu-central-1": "43",
        "eu-north-1": "43",
        "eu-west-1": "43",
        "eu-west-2": "43",
        "eu-west-3": "43",
        "sa-east-1": "43",
        "us-east-1": "43",
        "us-east-2": "43",
        "us-west-1": "43",
        "us-west-2": "43",
        "ap-east-1": "43",
        "ap-south-1": "43",
        "ap-northeast-1": "43",
        "ap-northeast-2": "43",
        "ap-northeast-3": "43",
        "ap-southeast-1": "43",
        "ap-southeast-2": "43",
        "eu-south-1": "43",
        "eu-south-2": "43",
        "af-south-1": "43",
        "me-south-1": "43"
    },
    "arm-php-80": {
        "ca-central-1": "65",
        "eu-central-1": "64",
        "eu-north-1": "65",
        "eu-west-1": "65",
        "eu-west-2": "65",
        "eu-west-3": "65",
        "sa-east-1": "65",
        "us-east-1": "65",
        "us-east-2": "65",
        "us-west-1": "65",
        "us-west-2": "65",
        "ap-east-1": "57",
        "ap-south-1": "64",
        "ap-northeast-1": "64",
        "ap-northeast-2": "64",
        "ap-northeast-3": "64",
        "ap-southeast-1": "64",
        "ap-southeast-2": "64",
        "eu-south-1": "57",
        "eu-south-2": "53",
        "af-south-1": "57",
        "me-south-1": "57"
    },
    "arm-php-80-fpm": {
        "ca-central-1": "64",
        "eu-central-1": "63",
        "eu-north-1": "64",
        "eu-west-1": "64",
        "eu-west-2": "63",
        "eu-west-3": "63",
        "sa-east-1": "63",
        "us-east-1": "64",
        "us-east-2": "64",
        "us-west-1": "63",
        "us-west-2": "64",
        "ap-east-1": "56",
        "ap-south-1": "62",
        "ap-northeast-1": "63",
        "ap-northeast-2": "62",
        "ap-northeast-3": "62",
        "ap-southeast-1": "62",
        "ap-southeast-2": "62",
        "eu-south-1": "55",
        "eu-south-2": "52",
        "af-south-1": "56",
        "me-south-1": "55"
    },
    "console": {
        "ca-central-1": "62",
        "eu-central-1": "62",
        "eu-north-1": "62",
        "eu-west-1": "62",
        "eu-west-2": "62",
        "eu-west-3": "62",
        "sa-east-1": "62",
        "us-east-1": "62",
        "us-east-2": "62",
        "us-west-1": "62",
        "us-west-2": "62",
        "ap-east-1": "54",
        "ap-south-1": "61",
        "ap-northeast-1": "61",
        "ap-northeast-2": "61",
        "ap-northeast-3": "61",
        "ap-southeast-1": "61",
        "ap-southeast-2": "61",
        "eu-south-1": "54",
        "eu-south-2": "51",
        "af-south-1": "54",
        "me-south-1": "54"
    }
}