{
    "php-83": {
        "ca-central-1": "17",
        "eu-central-1": "17",
        "eu-north-1": "17",
        "eu-west-1": "17",
        "eu-west-2": "17",
        "eu-west-3": "17",
        "sa-east-1": "17",
        "us-east-1": "17",
        "us-east-2": "17",
        "us-west-1": "17",
        "us-west-2": "17",
        "ap-east-1": "17",
        "ap-south-1": "17",
        "ap-northeast-1": "17",
        "ap-northeast-2": "17",
        "ap-northeast-3": "17",
        "ap-southeast-1": "17",
        "ap-southeast-2": "17",
        "eu-south-1": "17",
        "eu-south-2": "17",
        "af-south-1": "17",
        "me-south-1": "17"
    },
    "php-83-fpm": {
        "ca-central-1": "17",
        "eu-central-1": "17",
        "eu-north-1": "17",
        "eu-west-1": "17",
        "eu-west-2": "17",
        "eu-west-3": "17",
        "sa-east-1": "17",
        "us-east-1": "17",
        "us-east-2": "17",
        "us-west-1": "17",
        "us-west-2": "17",
        "ap-east-1": "17",
        "ap-south-1": "17",
        "ap-northeast-1": "17",
        "ap-northeast-2": "17",
        "ap-northeast-3": "17",
        "ap-southeast-1": "17",
        "ap-southeast-2": "17",
        "eu-south-1": "17",
        "eu-south-2": "17",
        "af-south-1": "17",
        "me-south-1": "17"
    },
    "php-82": {
        "ca-central-1": "61",
        "eu-central-1": "61",
        "eu-north-1": "61",
        "eu-west-1": "61",
        "eu-west-2": "61",
        "eu-west-3": "61",
        "sa-east-1": "61",
        "us-east-1": "61",
        "us-east-2": "61",
        "us-west-1": "61",
        "us-west-2": "61",
        "ap-east-1": "61",
        "ap-south-1": "61",
        "ap-northeast-1": "61",
        "ap-northeast-2": "61",
        "ap-northeast-3": "61",
        "ap-southeast-1": "61",
        "ap-southeast-2": "61",
        "eu-south-1": "61",
        "eu-south-2": "60",
        "af-south-1": "61",
        "me-south-1": "61"
    },
    "php-82-fpm": {
        "ca-central-1": "61",
        "eu-central-1": "61",
        "eu-north-1": "61",
        "eu-west-1": "61",
        "eu-west-2": "61",
        "eu-west-3": "61",
        "sa-east-1": "61",
        "us-east-1": "61",
        "us-east-2": "61",
        "us-west-1": "61",
        "us-west-2": "61",
        "ap-east-1": "61",
        "ap-south-1": "61",
        "ap-northeast-1": "61",
        "ap-northeast-2": "61",
        "ap-northeast-3": "61",
        "ap-southeast-1": "61",
        "ap-southeast-2": "61",
        "eu-south-1": "61",
        "eu-south-2": "60",
        "af-south-1": "61",
        "me-south-1": "61"
    },
    "php-81": {
        "ca-central-1": "72",
        "eu-central-1": "72",
        "eu-north-1": "72",
        "eu-west-1": "72",
        "eu-west-2": "72",
        "eu-west-3": "72",
        "sa-east-1": "72",
        "us-east-1": "72",
        "us-east-2": "72",
        "us-west-1": "72",
        "us-west-2": "72",
        "ap-east-1": "64",
        "ap-south-1": "71",
        "ap-northeast-1": "71",
        "ap-northeast-2": "71",
        "ap-northeast-3": "71",
        "ap-southeast-1": "71",
        "ap-southeast-2": "71",
        "eu-south-1": "64",
        "eu-south-2": "61",
        "af-south-1": "64",
        "me-south-1": "64"
    },
    "php-81-fpm": {
        "ca-central-1": "71",
        "eu-central-1": "71",
        "eu-north-1": "72",
        "eu-west-1": "72",
        "eu-west-2": "71",
        "eu-west-3": "71",
        "sa-east-1": "71",
        "us-east-1": "72",
        "us-east-2": "71",
        "us-west-1": "71",
        "us-west-2": "72",
        "ap-east-1": "64",
        "ap-south-1": "70",
        "ap-northeast-1": "71",
        "ap-northeast-2": "70",
        "ap-northeast-3": "70",
        "ap-southeast-1": "70",
        "ap-southeast-2": "70",
        "eu-south-1": "63",
        "eu-south-2": "60",
        "af-south-1": "63",
        "me-south-1": "63"
    },
    "php-80": {
        "ca-central-1": "75",
        "eu-central-1": "74",
        "eu-north-1": "75",
        "eu-west-1": "75",
        "eu-west-2": "75",
        "eu-west-3": "75",
        "sa-east-1": "75",
        "us-east-1": "75",
        "us-east-2": "75",
        "us-west-1": "75",
        "us-west-2": "75",
        "ap-east-1": "65",
        "ap-south-1": "74",
        "ap-northeast-1": "72",
        "ap-northeast-2": "71",
        "ap-northeast-3": "72",
        "ap-southeast-1": "71",
        "ap-southeast-2": "73",
        "eu-south-1": "65",
        "eu-south-2": "61",
        "af-south-1": "65",
        "me-south-1": "65"
    },
    "php-80-fpm": {
        "ca-central-1": "72",
        "eu-central-1": "72",
        "eu-north-1": "72",
        "eu-west-1": "72",
        "eu-west-2": "72",
        "eu-west-3": "72",
        "sa-east-1": "72",
        "us-east-1": "72",
        "us-east-2": "72",
        "us-west-1": "72",
        "us-west-2": "72",
        "ap-east-1": "64",
        "ap-south-1": "71",
        "ap-northeast-1": "71",
        "ap-northeast-2": "71",
        "ap-northeast-3": "71",
        "ap-southeast-1": "71",
        "ap-southeast-2": "71",
        "eu-south-1": "64",
        "eu-south-2": "61",
        "af-south-1": "64",
        "me-south-1": "64"
    },
    "arm-php-83": {
        "ca-central-1": "17",
        "eu-central-1": "17",
        "eu-north-1": "17",
        "eu-west-1": "17",
        "eu-west-2": "17",
        "eu-west-3": "17",
        "sa-east-1": "17",
        "us-east-1": "17",
        "us-east-2": "17",
        "us-west-1": "17",
        "us-west-2": "17",
        "ap-east-1": "17",
        "ap-south-1": "17",
        "ap-northeast-1": "17",
        "ap-northeast-2": "17",
        "ap-northeast-3": "17",
        "ap-southeast-1": "17",
        "ap-southeast-2": "17",
        "eu-south-1": "17",
        "eu-south-2": "17",
        "af-south-1": "17",
        "me-south-1": "17"
    },
    "arm-php-83-fpm": {
        "ca-central-1": "17",
        "eu-central-1": "17",
        "eu-north-1": "17",
        "eu-west-1": "17",
        "eu-west-2": "17",
        "eu-west-3": "17",
        "sa-east-1": "17",
        "us-east-1": "17",
        "us-east-2": "17",
        "us-west-1": "17",
        "us-west-2": "17",
        "ap-east-1": "17",
        "ap-south-1": "17",
        "ap-northeast-1": "17",
        "ap-northeast-2": "17",
        "ap-northeast-3": "17",
        "ap-southeast-1": "17",
        "ap-southeast-2": "17",
        "eu-south-1": "17",
        "eu-south-2": "17",
        "af-south-1": "17",
        "me-south-1": "17"
    },
    "arm-php-82": {
        "ca-central-1": "49",
        "eu-central-1": "49",
        "eu-north-1": "49",
        "eu-west-1": "49",
        "eu-west-2": "49",
        "eu-west-3": "49",
        "sa-east-1": "49",
        "us-east-1": "49",
        "us-east-2": "49",
        "us-west-1": "49",
        "us-west-2": "49",
        "ap-east-1": "49",
        "ap-south-1": "49",
        "ap-northeast-1": "49",
        "ap-northeast-2": "49",
        "ap-northeast-3": "49",
        "ap-southeast-1": "49",
        "ap-southeast-2": "49",
        "eu-south-1": "49",
        "eu-south-2": "49",
        "af-south-1": "49",
        "me-south-1": "49"
    },
    "arm-php-82-fpm": {
        "ca-central-1": "49",
        "eu-central-1": "49",
        "eu-north-1": "49",
        "eu-west-1": "49",
        "eu-west-2": "49",
        "eu-west-3": "49",
        "sa-east-1": "49",
        "us-east-1": "49",
        "us-east-2": "49",
        "us-west-1": "49",
        "us-west-2": "49",
        "ap-east-1": "49",
        "ap-south-1": "49",
        "ap-northeast-1": "49",
        "ap-northeast-2": "49",
        "ap-northeast-3": "49",
        "ap-southeast-1": "49",
        "ap-southeast-2": "49",
        "eu-south-1": "49",
        "eu-south-2": "49",
        "af-south-1": "49",
        "me-south-1": "49"
    },
    "arm-php-81": {
        "ca-central-1": "52",
        "eu-central-1": "52",
        "eu-north-1": "52",
        "eu-west-1": "52",
        "eu-west-2": "52",
        "eu-west-3": "52",
        "sa-east-1": "52",
        "us-east-1": "52",
        "us-east-2": "52",
        "us-west-1": "52",
        "us-west-2": "52",
        "ap-east-1": "52",
        "ap-south-1": "52",
        "ap-northeast-1": "52",
        "ap-northeast-2": "52",
        "ap-northeast-3": "52",
        "ap-southeast-1": "52",
        "ap-southeast-2": "52",
        "eu-south-1": "52",
        "eu-south-2": "52",
        "af-south-1": "52",
        "me-south-1": "52"
    },
    "arm-php-81-fpm": {
        "ca-central-1": "52",
        "eu-central-1": "52",
        "eu-north-1": "52",
        "eu-west-1": "52",
        "eu-west-2": "52",
        "eu-west-3": "52",
        "sa-east-1": "52",
        "us-east-1": "52",
        "us-east-2": "52",
        "us-west-1": "52",
        "us-west-2": "52",
        "ap-east-1": "52",
        "ap-south-1": "52",
        "ap-northeast-1": "52",
        "ap-northeast-2": "52",
        "ap-northeast-3": "52",
        "ap-southeast-1": "52",
        "ap-southeast-2": "52",
        "eu-south-1": "52",
        "eu-south-2": "52",
        "af-south-1": "52",
        "me-south-1": "52"
    },
    "arm-php-80": {
        "ca-central-1": "74",
        "eu-central-1": "73",
        "eu-north-1": "74",
        "eu-west-1": "74",
        "eu-west-2": "74",
        "eu-west-3": "74",
        "sa-east-1": "74",
        "us-east-1": "74",
        "us-east-2": "74",
        "us-west-1": "74",
        "us-west-2": "74",
        "ap-east-1": "66",
        "ap-south-1": "73",
        "ap-northeast-1": "73",
        "ap-northeast-2": "73",
        "ap-northeast-3": "73",
        "ap-southeast-1": "73",
        "ap-southeast-2": "73",
        "eu-south-1": "66",
        "eu-south-2": "62",
        "af-south-1": "66",
        "me-south-1": "66"
    },
    "arm-php-80-fpm": {
        "ca-central-1": "73",
        "eu-central-1": "72",
        "eu-north-1": "73",
        "eu-west-1": "73",
        "eu-west-2": "72",
        "eu-west-3": "72",
        "sa-east-1": "72",
        "us-east-1": "73",
        "us-east-2": "73",
        "us-west-1": "72",
        "us-west-2": "73",
        "ap-east-1": "65",
        "ap-south-1": "71",
        "ap-northeast-1": "72",
        "ap-northeast-2": "71",
        "ap-northeast-3": "71",
        "ap-southeast-1": "71",
        "ap-southeast-2": "71",
        "eu-south-1": "64",
        "eu-south-2": "61",
        "af-south-1": "65",
        "me-south-1": "64"
    },
    "console": {
        "ca-central-1": "71",
        "eu-central-1": "71",
        "eu-north-1": "71",
        "eu-west-1": "71",
        "eu-west-2": "71",
        "eu-west-3": "71",
        "sa-east-1": "71",
        "us-east-1": "71",
        "us-east-2": "71",
        "us-west-1": "71",
        "us-west-2": "71",
        "ap-east-1": "63",
        "ap-south-1": "70",
        "ap-northeast-1": "70",
        "ap-northeast-2": "70",
        "ap-northeast-3": "70",
        "ap-southeast-1": "70",
        "ap-southeast-2": "70",
        "eu-south-1": "63",
        "eu-south-2": "60",
        "af-south-1": "63",
        "me-south-1": "63"
    }
}